{
    "1645338852782945:4783882": {
        "RenderOrderComponent": true
    },
    "1645338852859579:4784394": {
        "InspectorComponent": {
            "Component.ScreenTransform": {
                "basicModeSetup": {
                    "attachBottom": "false",
                    "attachLeft": "false",
                    "attachRight": "false",
                    "attachTop": "false",
                    "fixHeight": "false",
                    "fixWidth": "false"
                },
                "isBasicMode": "true"
            }
        }
    }
}
