{
    "1646076339824731:2312799": {
        "RenderOrderComponent": true
    },
    "1646076339844054:2313059": {
        "InspectorComponent": {
            "Component.ScreenTransform": {
                "basicModeSetup": {
                    "attachBottom": "false",
                    "attachLeft": "false",
                    "attachRight": "false",
                    "attachTop": "false",
                    "fixHeight": "true",
                    "fixWidth": "true"
                },
                "isBasicMode": "true"
            }
        }
    }
}
