{
    "1536261203342130:248973": {
        "Compression::IController": {
            "compressed_files": "",
            "infos": {
                "compressedRAM": "1002",
                "compressedSize": "1075",
                "extension": "mesh",
                "originalRAM": "1002",
                "originalSize": "1075",
                "settings": {
                    "attributeFormat": "",
                    "draco": {
                        "colorBits": "8",
                        "compressLvl": "7",
                        "normalBits": "8",
                        "posBits": "11",
                        "texBits": "10"
                    },
                    "info": {
                        "hasBlendShapes": "false",
                        "vertexAttribs": [
                            {
                                "canBeDisabled": "false",
                                "format": "9",
                                "semantic": "position"
                            },
                            {
                                "canBeDisabled": "true",
                                "format": "9",
                                "semantic": "normal"
                            },
                            {
                                "canBeDisabled": "true",
                                "format": "9",
                                "semantic": "tangent"
                            },
                            {
                                "canBeDisabled": "true",
                                "format": "9",
                                "semantic": "texture0"
                            }
                        ]
                    },
                    "isCompressed": "false",
                    "type": "0"
                }
            },
            "uncompressed_file": "1682218046377881:37238"
        }
    },
    "1682218046376565:35640": {
        "IResourceController": {
            "name": "In_Piece_41",
            "type": 3,
            "subtype": 0,
            "dependency": 0,
            "hidden": false,
            "uid": "1536261203342130:248973",
            "fileId": "1682218046376891:36538",
            "publicId": "1682218046378665:37815",
            "expected_hash": "bb538e5d43b5918e53987d46135a981c"
        },
        "IResourceManager": {
            "uid": "1536261203342130:248973",
            "name": "/Resources/Resource546.mesh",
            "flags": 21
        }
    },
    "1682218046376891:36538": {
        "IFileManager": {
            "path": "Files/File_1682218046376891_36538.mesh"
        }
    },
    "1682218046377881:37238": {
        "IFileManager": {
            "path": "Files/File_1682218046377881_37238.mesh"
        }
    },
    "1682218046378665:37815": {
        "IResourceController": {
            "public": {
                "path": "Meshes/Explode/Meshes/In_Piece_41.mesh",
                "hash": "bb538e5d43b5918e53987d46135a981c"
            }
        }
    }
}
